mistral_sae/activationsLoader.py
mistral_sae/config.py
mistral_sae/generate.py
mistral_sae/liveDataloader.py
mistral_sae/model.py
mistral_sae/sae.py
mistral_sae-0.1.3.dist-info/METADATA
mistral_sae-0.1.3.dist-info/WHEEL
mistral_sae-0.1.3.dist-info/RECORD
