Metadata-Version: 2.1
Name: mistral-sae
Version: 0.1.3
Summary: Sparse AutoEncoder to decode Mistral LLM
License: MIT
Author: seonglae
Author-email: sungle3737@gmail.com
Requires-Python: >=3.9.10,<4.0
Classifier: License :: OSI Approved :: MIT License
Classifier: Programming Language :: Python :: 3
Classifier: Programming Language :: Python :: 3.10
Classifier: Programming Language :: Python :: 3.11
Classifier: Programming Language :: Python :: 3.12
Requires-Dist: mistral-common (>=1.4.4,<2.0.0)
Requires-Dist: mistral-inference (>=1.4.0,<2.0.0)
Requires-Dist: mistralai (>=1.1.0,<2.0.0)
Requires-Dist: torch (>=2.4.1,<3.0.0)
Requires-Dist: transformer-lens (>=2.7.0,<3.0.0)
Requires-Dist: transformers (>=4.45.2,<5.0.0)
Requires-Dist: xformers (>=0.0.28,<0.0.29)
